byted_rig_libra/__init__.py
byted_rig_libra-0.0.1.dist-info/METADATA
byted_rig_libra-0.0.1.dist-info/WHEEL
byted_rig_libra-0.0.1.dist-info/top_level.txt
byted_rig_libra-0.0.1.dist-info/RECORD
